indentalog/__init__.py
indentalog/config.py
indentalog/ilogger.py
indentalog/wrappers/__init__.py
indentalog/wrappers/callpoint.py
indentalog/wrappers/decorator.py
indentalog/wrappers/endpoint.py
indentalog/wrappers/iterable.py
indentalog-0.1.3.dist-info/LICENSE
indentalog-0.1.3.dist-info/METADATA
indentalog-0.1.3.dist-info/WHEEL
indentalog-0.1.3.dist-info/RECORD
